blueplate/__init__.py
blueplate/__main__.py
blueplate/version.py
blueplate/blueplate/__init__.py
blueplate/blueplate/defaults.toml
blueplate/blueplate/imports.py
blueplate/blueplate/logger.py
blueplate/blueplate/special.py
blueplate/blueplate/version.py
blueplate-0.1.12.dist-info/LICENSE
blueplate-0.1.12.dist-info/METADATA
blueplate-0.1.12.dist-info/WHEEL
blueplate-0.1.12.dist-info/top_level.txt
blueplate-0.1.12.dist-info/RECORD
