Metadata-Version: 2.1
Name: blueplate
Version: 0.1.12
Summary: a blueprint for sensible command line tools
Home-page: https://github.com/lawnmowerlatte/blueplate
Author: lawnmowerlatte
Author-email: lawnmowerlatte@gmail.com
Project-URL: Bug Tracker, https://github.com/lawnmowerlatte/blueplate/issues
Classifier: Programming Language :: Python :: 3
Classifier: License :: OSI Approved :: MIT License
Classifier: Operating System :: OS Independent
Requires-Python: >=3.10
License-File: LICENSE
